{"_id":"oauth-sign","_rev":"7-ca8604fc3bd569061774dd29f20d5b32","name":"oauth-sign","description":"OAuth 1 signing. Formerly a vendor lib in mikeal/request, now a standalone module.","dist-tags":{"latest":"0.4.0"},"versions":{"0.2.0":{"author":{"name":"Mikeal Rogers","email":"mikeal.rogers@gmail.com","url":"http://www.futurealoof.com"},"name":"oauth-sign","description":"OAuth 1 signing. Formerly a vendor lib in mikeal/request, now a standalone module.","version":"0.2.0","repository":{"url":"https://github.com/mikeal/oauth-sign"},"main":"index.js","dependencies":{},"devDependencies":{},"optionalDependencies":{},"engines":{"node":"*"},"scripts":{"test":"node test.js"},"_npmUser":{"name":"mikeal","email":"mikeal.rogers@gmail.com"},"_id":"oauth-sign@0.2.0","_engineSupported":true,"_npmVersion":"1.1.24","_nodeVersion":"v0.8.1","_defaultsLoaded":true,"dist":{"shasum":"a0e6a1715daed062f322b622b7fe5afd1035b6e2","tarball":"http://registry.npmjs.org/oauth-sign/-/oauth-sign-0.2.0.tgz"},"readme":"","maintainers":[{"name":"mikeal","email":"mikeal.rogers@gmail.com"}],"directories":{}},"0.3.0":{"author":{"name":"Mikeal Rogers","email":"mikeal.rogers@gmail.com","url":"http://www.futurealoof.com"},"name":"oauth-sign","description":"OAuth 1 signing. Formerly a vendor lib in mikeal/request, now a standalone module.","version":"0.3.0","repository":{"url":"https://github.com/mikeal/oauth-sign"},"main":"index.js","dependencies":{},"devDependencies":{},"optionalDependencies":{},"engines":{"node":"*"},"scripts":{"test":"node test.js"},"readme":"oauth-sign\n==========\n\nOAuth 1 signing. Formerly a vendor lib in mikeal/request, now a standalone module. \n","readmeFilename":"README.md","_id":"oauth-sign@0.3.0","dist":{"shasum":"cb540f93bb2b22a7d5941691a288d60e8ea9386e","tarball":"http://registry.npmjs.org/oauth-sign/-/oauth-sign-0.3.0.tgz"},"_from":".","_npmVersion":"1.2.14","_npmUser":{"name":"mikeal","email":"mikeal.rogers@gmail.com"},"maintainers":[{"name":"mikeal","email":"mikeal.rogers@gmail.com"}],"directories":{}},"0.4.0":{"author":{"name":"Mikeal Rogers","email":"mikeal.rogers@gmail.com","url":"http://www.futurealoof.com"},"name":"oauth-sign","description":"OAuth 1 signing. Formerly a vendor lib in mikeal/request, now a standalone module.","version":"0.4.0","repository":{"url":"https://github.com/mikeal/oauth-sign"},"main":"index.js","dependencies":{},"devDependencies":{},"optionalDependencies":{},"engines":{"node":"*"},"scripts":{"test":"node test.js"},"readme":"oauth-sign\n==========\n\nOAuth 1 signing. Formerly a vendor lib in mikeal/request, now a standalone module. \n","readmeFilename":"README.md","bugs":{"url":"https://github.com/mikeal/oauth-sign/issues"},"_id":"oauth-sign@0.4.0","dist":{"shasum":"f22956f31ea7151a821e5f2fb32c113cad8b9f69","tarball":"http://registry.npmjs.org/oauth-sign/-/oauth-sign-0.4.0.tgz"},"_from":".","_npmVersion":"1.3.2","_npmUser":{"name":"mikeal","email":"mikeal.rogers@gmail.com"},"maintainers":[{"name":"mikeal","email":"mikeal.rogers@gmail.com"}],"directories":{}}},"readme":"","maintainers":[{"name":"mikeal","email":"mikeal.rogers@gmail.com"}],"time":{"0.2.0":"2013-03-01T20:23:20.779Z","0.3.0":"2013-04-22T05:12:37.269Z","0.4.0":"2013-09-23T22:58:47.722Z"},"author":{"name":"Mikeal Rogers","email":"mikeal.rogers@gmail.com","url":"http://www.futurealoof.com"},"repository":{"url":"https://github.com/mikeal/oauth-sign"},"_attachments":{"oauth-sign-0.4.0.tgz":{"content_type":"application/octet-stream","revpos":6,"digest":"md5-1Qz5fe/WL9YHGBdawSYK4g==","length":5978,"stub":true},"oauth-sign-0.3.0.tgz":{"content_type":"application/octet-stream","revpos":4,"digest":"md5-qxHh+PrhdmWfSgkVzGsLnw==","length":5248,"stub":true},"oauth-sign-0.2.0.tgz":{"content_type":"application/octet-stream","revpos":3,"digest":"md5-pvrT3Xm2cYCLAGb2jPPIDw==","length":1854,"stub":true}},"_etag":"\"5RZFAWHQV0C14Q8D0ZU11GL0O\""}