{"_id":"bower-registry-client","_rev":"32-8d99951399e1a153725bd0995dd82b80","name":"bower-registry-client","description":"Provides easy interaction with the Bower registry.","dist-tags":{"latest":"0.1.6"},"versions":{"0.1.0-rc.1":{"name":"bower-registry-client","version":"0.1.0-rc.1","description":"Provides easy interaction with the Bower registry.","author":{"name":"Twitter"},"licenses":[{"type":"MIT","url":"https://github.com/bower/registry-client/blob/master/LICENSE"}],"repository":{"type":"git","url":"git://github.com/bower/registry-client.git"},"main":"Client","engines":{"node":">=0.8.0"},"dependencies":{"async":"~0.2.8","graceful-fs":"~1.2.2","lru-cache":"~2.3.0","request":"~2.21.0","rimraf":"~2.1.4","mkdirp":"~0.3.5"},"devDependencies":{"chai":"~1.7.2","expect.js":"~0.2.0","grunt":"~0.4.1","grunt-contrib-watch":"~0.4.4","grunt-contrib-jshint":"~0.6.0","grunt-simple-mocha":"~0.4.0","mocha":"~1.12.0","nock":"~0.18.2"},"scripts":{"test":"grunt test"},"readme":"# bower-registry-client [![Build Status](https://secure.travis-ci.org/bower/registry-client.png?branch=master)](http://travis-ci.org/bower/registry-client)\n\nThis module allows you to easily interact with the Bower server API.\n\n\n## Usage\n\n```js\n\nvar RegistryClient = require('bower-registry-client');\nvar registry = new RegistryClient(options);\n```\n\nAvailable constructor options:\n\n- `cache`: the cache folder to use for some operations; using null will disable  persistent cache (defaults to OS temp folder)\n- `registry.search`: an array of registry search endpoints (defaults to the Bower server)\n- `registry.register`: the endpoint to use when registering packages (defaults to the Bower server)\n- `registry.publish`: the endpoint to use when publishing packages (defaults to the Bower server)\n- `ca.search`: an array of CA certificates for each registry.search (defaults to null).\n- `ca.register`: the CA certificate for registry.register\n- `ca.publish`: the CA certificate for registry.publish\n- `proxy`: the proxy to use for http requests (defaults to null)\n- `httpsProxy`: the proxy to use for https requests (defaults to null)\n- `strictSsl`: whether or not to do SSL key validation when making requests via https (defaults to true).\n- `userAgent`: the user agent to use for the requests (defaults to null)\n- `timeout`: the timeout for the requests to finish (defaults to 5000)\n- `force`: If set to true, cache will be bypassed and remotes will always be hit (defaults to false).\n- `offline`: If set to true, only the cache will be used (defaults to false).\n\n\nNote that `force` and `offline` are mutually exclusive.\nThe cache will speedup operations such as `lookup` and `info`.\nDifferent operations may have different cache expiration times.\n\n\n#### .lookup(name, callback)\n\nLooks the registry for the package `name`,\n\n```js\nregistry.lookup('jquery', function (err, entry) {\n    if (err) {\n        console.error(err.message);\n        return;\n    }\n\n    // For now resp.type is always 'alias'\n    console.log('type', entry.type);\n    console.log('url', entry.url);\n});\n```\n\n#### .register(name, url, callback)\n\nRegisters a package in the registry.\n\n```js\nregistry.register('my-package', 'git://github.com/my-org/my-package.git', function (err, pkg) {\n    if (err) {\n        console.error(err.message);\n        return;\n    }\n\n    console.log('name', pkg.name);\n    console.log('url: ', pkg.url);\n});\n```\n\n#### .search(str, callback)\n\nSearches the registry.\n\n```js\nregistry.search('jquery', function (err, results) {\n    if (err) {\n        console.error(err.message);\n        return;\n    }\n\n    results.forEach(function (pkg) {\n        console.log('name', pkg.name);\n        console.log('url', pkg.url);\n    });\n});\n```\n\n#### .clearCache(name, callback)\n\nClears the persistent and runtime cache associated with the `name` package.   \nIf `name` is null, clears the cache for every package.\n\nNote that in most cases, you don't need to clear the cache since it has\nself expiration times.\n\n```js\n// Clear jquery cache\nregistry.clearCache('jquery', function (err) {\n    if (err) {\n        console.error(err.message);\n        return;\n    }\n\n    console.log('Done');\n});\n\n// Clear all cache\nregistry.clearCache(function (err) {\n    if (err) {\n        console.error(err.message);\n        return;\n    }\n\n    console.log('Done');\n});\n```\n\n\n#### .resetCache()\n\nClears the in-memory cache used to speed up the instance.\n\nNote that in most cases, you don't need to clear the runtime cache since it has\nself expiration times.\nMight be useful if you use this module in long-living programs.\n\n```js\nregistry.resetCache();\n```\n\n#### #clearRuntimeCache()\n\nClears the in-memory cache used to speed up the whole module.\nThis clears the static in-memory cache as well as in-memory cache used by instances.\n\nNote that in edge cases, some instance's in-memory cache might be skipped.\nIf that's a problem, you should create fresh instances instead.\n\n```js\nRegistryClient.clearRuntimeCache();\n```\n\n\n\n## License\n\nReleased under the [MIT License](http://www.opensource.org/licenses/mit-license.php).\n","readmeFilename":"README.md","bugs":{"url":"https://github.com/bower/registry-client/issues"},"_id":"bower-registry-client@0.1.0-rc.1","dist":{"shasum":"4615ddcb307258e72e76a34d38ff48a38e5d0c1a","tarball":"http://registry.npmjs.org/bower-registry-client/-/bower-registry-client-0.1.0-rc.1.tgz"},"_from":".","_npmVersion":"1.2.32","_npmUser":{"name":"satazor","email":"andremiguelcruz@msn.com"},"maintainers":[{"name":"satazor","email":"andremiguelcruz@msn.com"}],"directories":{}},"0.1.0-rc.2":{"name":"bower-registry-client","version":"0.1.0-rc.2","description":"Provides easy interaction with the Bower registry.","author":{"name":"Twitter"},"licenses":[{"type":"MIT","url":"https://github.com/bower/registry-client/blob/master/LICENSE"}],"repository":{"type":"git","url":"git://github.com/bower/registry-client.git"},"main":"Client","engines":{"node":">=0.8.0"},"dependencies":{"async":"~0.2.8","graceful-fs":"~1.2.2","lru-cache":"~2.3.0","request":"~2.21.0","rimraf":"~2.1.4","mkdirp":"~0.3.5"},"devDependencies":{"expect.js":"~0.2.0","grunt":"~0.4.1","grunt-contrib-watch":"~0.4.4","grunt-contrib-jshint":"~0.6.0","grunt-simple-mocha":"~0.4.0","mocha":"~1.12.0","nock":"~0.18.2"},"scripts":{"test":"grunt test"},"readme":"# bower-registry-client [![Build Status](https://secure.travis-ci.org/bower/registry-client.png?branch=master)](http://travis-ci.org/bower/registry-client)\n\nThis module allows you to easily interact with the Bower server API.\n\n\n## Usage\n\n```js\n\nvar RegistryClient = require('bower-registry-client');\nvar registry = new RegistryClient(options);\n```\n\nAvailable constructor options:\n\n- `cache`: the cache folder to use for some operations; using null will disable  persistent cache (defaults to OS temp folder)\n- `registry.search`: an array of registry search endpoints (defaults to the Bower server)\n- `registry.register`: the endpoint to use when registering packages (defaults to the Bower server)\n- `registry.publish`: the endpoint to use when publishing packages (defaults to the Bower server)\n- `ca.search`: an array of CA certificates for each registry.search (defaults to null).\n- `ca.register`: the CA certificate for registry.register\n- `ca.publish`: the CA certificate for registry.publish\n- `proxy`: the proxy to use for http requests (defaults to null)\n- `httpsProxy`: the proxy to use for https requests (defaults to null)\n- `strictSsl`: whether or not to do SSL key validation when making requests via https (defaults to true).\n- `userAgent`: the user agent to use for the requests (defaults to null)\n- `timeout`: the timeout for the requests to finish (defaults to 5000)\n- `force`: If set to true, cache will be bypassed and remotes will always be hit (defaults to false).\n- `offline`: If set to true, only the cache will be used (defaults to false).\n\n\nNote that `force` and `offline` are mutually exclusive.\nThe cache will speedup operations such as `list`, `lookup` and `search`.\nDifferent operations may have different cache expiration times.\n\n\n#### .lookup(name, callback)\n\nLooks the registry for the package `name`,\n\n```js\nregistry.lookup('jquery', function (err, entry) {\n    if (err) {\n        console.error(err.message);\n        return;\n    }\n\n    // For now resp.type is always 'alias'\n    console.log('type', entry.type);\n    console.log('url', entry.url);\n});\n```\n\n#### .register(name, url, callback)\n\nRegisters a package in the registry.\n\n```js\nregistry.register('my-package', 'git://github.com/my-org/my-package.git', function (err, pkg) {\n    if (err) {\n        console.error(err.message);\n        return;\n    }\n\n    console.log('name', pkg.name);\n    console.log('url: ', pkg.url);\n});\n```\n\n#### .search(str, callback)\n\nSearches the registry.\n\n```js\nregistry.search('jquery', function (err, results) {\n    if (err) {\n        console.error(err.message);\n        return;\n    }\n\n    results.forEach(function (pkg) {\n        console.log('name', pkg.name);\n        console.log('url', pkg.url);\n    });\n});\n```\n\n#### .clearCache(name, callback)\n\nClears the persistent and runtime cache associated with the `name` package.   \nIf `name` is null, clears the cache for every package.\n\nNote that in most cases, you don't need to clear the cache since it has\nself expiration times.\n\n```js\n// Clear jquery cache\nregistry.clearCache('jquery', function (err) {\n    if (err) {\n        console.error(err.message);\n        return;\n    }\n\n    console.log('Done');\n});\n\n// Clear all cache\nregistry.clearCache(function (err) {\n    if (err) {\n        console.error(err.message);\n        return;\n    }\n\n    console.log('Done');\n});\n```\n\n\n#### .resetCache()\n\nClears the in-memory cache used to speed up the instance.\n\nNote that in most cases, you don't need to clear the runtime cache since it has\nself expiration times.\nMight be useful if you use this module in long-living programs.\n\n```js\nregistry.resetCache();\n```\n\n#### #clearRuntimeCache()\n\nClears the in-memory cache used to speed up the whole module.\nThis clears the static in-memory cache as well as in-memory cache used by instances.\n\nNote that in edge cases, some instance's in-memory cache might be skipped.\nIf that's a problem, you should create fresh instances instead.\n\n```js\nRegistryClient.clearRuntimeCache();\n```\n\n\n\n## License\n\nReleased under the [MIT License](http://www.opensource.org/licenses/mit-license.php).\n","readmeFilename":"README.md","bugs":{"url":"https://github.com/bower/registry-client/issues"},"_id":"bower-registry-client@0.1.0-rc.2","dist":{"shasum":"82b5172fbb28c907a0faae2eebd171b1ac41eca7","tarball":"http://registry.npmjs.org/bower-registry-client/-/bower-registry-client-0.1.0-rc.2.tgz"},"_from":".","_npmVersion":"1.3.2","_npmUser":{"name":"satazor","email":"andremiguelcruz@msn.com"},"maintainers":[{"name":"satazor","email":"andremiguelcruz@msn.com"}],"directories":{}},"0.1.0-rc.3":{"name":"bower-registry-client","version":"0.1.0-rc.3","description":"Provides easy interaction with the Bower registry.","author":{"name":"Twitter"},"licenses":[{"type":"MIT","url":"https://github.com/bower/registry-client/blob/master/LICENSE"}],"repository":{"type":"git","url":"git://github.com/bower/registry-client.git"},"main":"Client","engines":{"node":">=0.8.0"},"dependencies":{"async":"~0.2.8","graceful-fs":"~2.0.0","lru-cache":"~2.3.0","request":"~2.22.0","request-replay":"~0.1.0","rimraf":"~2.2.0","mkdirp":"~0.3.5"},"devDependencies":{"expect.js":"~0.2.0","grunt":"~0.4.1","grunt-contrib-watch":"~0.4.4","grunt-contrib-jshint":"~0.6.0","grunt-simple-mocha":"~0.4.0","mocha":"~1.12.0","nock":"~0.18.2"},"scripts":{"test":"grunt test"},"readme":"# bower-registry-client [![Build Status](https://secure.travis-ci.org/bower/registry-client.png?branch=master)](http://travis-ci.org/bower/registry-client)\n\nThis module allows you to easily interact with the Bower server API.\n\n\n## Usage\n\n```js\n\nvar RegistryClient = require('bower-registry-client');\nvar registry = new RegistryClient(options);\n```\n\nAvailable constructor options:\n\n- `cache`: the cache folder to use for some operations; using null will disable  persistent cache (defaults to OS temp folder)\n- `registry.search`: an array of registry search endpoints (defaults to the Bower server)\n- `registry.register`: the endpoint to use when registering packages (defaults to the Bower server)\n- `registry.publish`: the endpoint to use when publishing packages (defaults to the Bower server)\n- `ca.search`: an array of CA certificates for each registry.search (defaults to null).\n- `ca.register`: the CA certificate for registry.register\n- `ca.publish`: the CA certificate for registry.publish\n- `proxy`: the proxy to use for http requests (defaults to null)\n- `httpsProxy`: the proxy to use for https requests (defaults to null)\n- `strictSsl`: whether or not to do SSL key validation when making requests via https (defaults to true).\n- `userAgent`: the user agent to use for the requests (defaults to null)\n- `timeout`: the timeout for the requests to finish (defaults to 5000)\n- `force`: If set to true, cache will be bypassed and remotes will always be hit (defaults to false).\n- `offline`: If set to true, only the cache will be used (defaults to false).\n\n\nNote that `force` and `offline` are mutually exclusive.\nThe cache will speedup operations such as `list`, `lookup` and `search`.\nDifferent operations may have different cache expiration times.\n\n\n#### .lookup(name, callback)\n\nLooks the registry for the package `name`,\n\n```js\nregistry.lookup('jquery', function (err, entry) {\n    if (err) {\n        console.error(err.message);\n        return;\n    }\n\n    // For now resp.type is always 'alias'\n    console.log('type', entry.type);\n    console.log('url', entry.url);\n});\n```\n\n#### .register(name, url, callback)\n\nRegisters a package in the registry.\n\n```js\nregistry.register('my-package', 'git://github.com/my-org/my-package.git', function (err, pkg) {\n    if (err) {\n        console.error(err.message);\n        return;\n    }\n\n    console.log('name', pkg.name);\n    console.log('url: ', pkg.url);\n});\n```\n\n#### .search(str, callback)\n\nSearches the registry.\n\n```js\nregistry.search('jquery', function (err, results) {\n    if (err) {\n        console.error(err.message);\n        return;\n    }\n\n    results.forEach(function (pkg) {\n        console.log('name', pkg.name);\n        console.log('url', pkg.url);\n    });\n});\n```\n\n#### .clearCache(name, callback)\n\nClears the persistent and runtime cache associated with the `name` package.   \nIf `name` is null, clears the cache for every package.\n\nNote that in most cases, you don't need to clear the cache since it has\nself expiration times.\n\n```js\n// Clear jquery cache\nregistry.clearCache('jquery', function (err) {\n    if (err) {\n        console.error(err.message);\n        return;\n    }\n\n    console.log('Done');\n});\n\n// Clear all cache\nregistry.clearCache(function (err) {\n    if (err) {\n        console.error(err.message);\n        return;\n    }\n\n    console.log('Done');\n});\n```\n\n\n#### .resetCache()\n\nClears the in-memory cache used to speed up the instance.\n\nNote that in most cases, you don't need to clear the runtime cache since it has\nself expiration times.\nMight be useful if you use this module in long-living programs.\n\n```js\nregistry.resetCache();\n```\n\n#### #clearRuntimeCache()\n\nClears the in-memory cache used to speed up the whole module.\nThis clears the static in-memory cache as well as in-memory cache used by instances.\n\nNote that in edge cases, some instance's in-memory cache might be skipped.\nIf that's a problem, you should create fresh instances instead.\n\n```js\nRegistryClient.clearRuntimeCache();\n```\n\n\n\n## License\n\nReleased under the [MIT License](http://www.opensource.org/licenses/mit-license.php).\n","readmeFilename":"README.md","bugs":{"url":"https://github.com/bower/registry-client/issues"},"_id":"bower-registry-client@0.1.0-rc.3","dist":{"shasum":"2dd7b378041965ab06d154a4fc77f5be8b5c5e7a","tarball":"http://registry.npmjs.org/bower-registry-client/-/bower-registry-client-0.1.0-rc.3.tgz"},"_from":".","_npmVersion":"1.3.2","_npmUser":{"name":"satazor","email":"andremiguelcruz@msn.com"},"maintainers":[{"name":"satazor","email":"andremiguelcruz@msn.com"}],"directories":{}},"0.1.0-rc.4":{"name":"bower-registry-client","version":"0.1.0-rc.4","description":"Provides easy interaction with the Bower registry.","author":{"name":"Twitter"},"licenses":[{"type":"MIT","url":"https://github.com/bower/registry-client/blob/master/LICENSE"}],"repository":{"type":"git","url":"git://github.com/bower/registry-client.git"},"main":"Client","engines":{"node":">=0.8.0"},"dependencies":{"async":"~0.2.8","graceful-fs":"~2.0.0","lru-cache":"~2.3.0","request":"~2.22.0","request-replay":"~0.1.0","rimraf":"~2.2.0","mkdirp":"~0.3.5"},"devDependencies":{"expect.js":"~0.2.0","grunt":"~0.4.1","grunt-contrib-watch":"~0.4.4","grunt-contrib-jshint":"~0.6.0","grunt-simple-mocha":"~0.4.0","mocha":"~1.12.0","nock":"~0.18.2"},"scripts":{"test":"grunt test"},"readme":"# bower-registry-client [![Build Status](https://secure.travis-ci.org/bower/registry-client.png?branch=master)](http://travis-ci.org/bower/registry-client)\n\nThis module allows you to easily interact with the Bower server API.\n\n\n## Usage\n\n```js\n\nvar RegistryClient = require('bower-registry-client');\nvar registry = new RegistryClient(options, logger);\n```\n\nThe `logger` is optional and is expected to be an instance of the bower [logger](https://github.com/bower/logger).   \nAvailable constructor options:\n\n- `cache`: the cache folder to use for some operations; using null will disable  persistent cache (defaults to OS temp folder)\n- `registry.search`: an array of registry search endpoints (defaults to the Bower server)\n- `registry.register`: the endpoint to use when registering packages (defaults to the Bower server)\n- `registry.publish`: the endpoint to use when publishing packages (defaults to the Bower server)\n- `ca.search`: an array of CA certificates for each registry.search (defaults to null).\n- `ca.register`: the CA certificate for registry.register\n- `ca.publish`: the CA certificate for registry.publish\n- `proxy`: the proxy to use for http requests (defaults to null)\n- `httpsProxy`: the proxy to use for https requests (defaults to null)\n- `strictSsl`: whether or not to do SSL key validation when making requests via https (defaults to true).\n- `userAgent`: the user agent to use for the requests (defaults to null)\n- `timeout`: the timeout for the requests to finish (defaults to 5000)\n- `force`: If set to true, cache will be bypassed and remotes will always be hit (defaults to false).\n- `offline`: If set to true, only the cache will be used (defaults to false).\n\n\nNote that `force` and `offline` are mutually exclusive.\nThe cache will speedup operations such as `list`, `lookup` and `search`.\nDifferent operations may have different cache expiration times.\n\n\n#### .lookup(name, callback)\n\nLooks the registry for the package `name`,\n\n```js\nregistry.lookup('jquery', function (err, entry) {\n    if (err) {\n        console.error(err.message);\n        return;\n    }\n\n    // For now resp.type is always 'alias'\n    console.log('type', entry.type);\n    console.log('url', entry.url);\n});\n```\n\n#### .register(name, url, callback)\n\nRegisters a package in the registry.\n\n```js\nregistry.register('my-package', 'git://github.com/my-org/my-package.git', function (err, pkg) {\n    if (err) {\n        console.error(err.message);\n        return;\n    }\n\n    console.log('name', pkg.name);\n    console.log('url: ', pkg.url);\n});\n```\n\n#### .search(str, callback)\n\nSearches the registry.\n\n```js\nregistry.search('jquery', function (err, results) {\n    if (err) {\n        console.error(err.message);\n        return;\n    }\n\n    results.forEach(function (pkg) {\n        console.log('name', pkg.name);\n        console.log('url', pkg.url);\n    });\n});\n```\n\n#### .clearCache(name, callback)\n\nClears the persistent and runtime cache associated with the `name` package.   \nIf `name` is null, clears the cache for every package.\n\nNote that in most cases, you don't need to clear the cache since it has\nself expiration times.\n\n```js\n// Clear jquery cache\nregistry.clearCache('jquery', function (err) {\n    if (err) {\n        console.error(err.message);\n        return;\n    }\n\n    console.log('Done');\n});\n\n// Clear all cache\nregistry.clearCache(function (err) {\n    if (err) {\n        console.error(err.message);\n        return;\n    }\n\n    console.log('Done');\n});\n```\n\n\n#### .resetCache()\n\nClears the in-memory cache used to speed up the instance.\n\nNote that in most cases, you don't need to clear the runtime cache since it has\nself expiration times.\nMight be useful if you use this module in long-living programs.\n\n```js\nregistry.resetCache();\n```\n\n#### #clearRuntimeCache()\n\nClears the in-memory cache used to speed up the whole module.\nThis clears the static in-memory cache as well as in-memory cache used by instances.\n\nNote that in edge cases, some instance's in-memory cache might be skipped.\nIf that's a problem, you should create fresh instances instead.\n\n```js\nRegistryClient.clearRuntimeCache();\n```\n\n\n\n## License\n\nReleased under the [MIT License](http://www.opensource.org/licenses/mit-license.php).\n","readmeFilename":"README.md","bugs":{"url":"https://github.com/bower/registry-client/issues"},"_id":"bower-registry-client@0.1.0-rc.4","dist":{"shasum":"4fd0dbaf1abdba0323cdbc08467f2e920b6d9fd1","tarball":"http://registry.npmjs.org/bower-registry-client/-/bower-registry-client-0.1.0-rc.4.tgz"},"_from":".","_npmVersion":"1.3.2","_npmUser":{"name":"satazor","email":"andremiguelcruz@msn.com"},"maintainers":[{"name":"satazor","email":"andremiguelcruz@msn.com"}],"directories":{}},"0.1.0-rc.5":{"name":"bower-registry-client","version":"0.1.0-rc.5","description":"Provides easy interaction with the Bower registry.","author":{"name":"Twitter"},"licenses":[{"type":"MIT","url":"https://github.com/bower/registry-client/blob/master/LICENSE"}],"repository":{"type":"git","url":"git://github.com/bower/registry-client.git"},"main":"Client","engines":{"node":">=0.8.0"},"dependencies":{"async":"~0.2.8","deep-extend":"~0.2.5","graceful-fs":"~2.0.0","lru-cache":"~2.3.0","request":"~2.22.0","request-replay":"~0.1.0","rimraf":"~2.2.0","mkdirp":"~0.3.5"},"devDependencies":{"expect.js":"~0.2.0","grunt":"~0.4.1","grunt-contrib-watch":"~0.5.0","grunt-contrib-jshint":"~0.6.0","grunt-simple-mocha":"~0.4.0","mocha":"~1.12.0","nock":"~0.22.0"},"scripts":{"test":"grunt test"},"readme":"# bower-registry-client [![Build Status](https://secure.travis-ci.org/bower/registry-client.png?branch=master)](http://travis-ci.org/bower/registry-client)\n\nThis module allows you to easily interact with the Bower server API.\n\n\n## Usage\n\n```js\n\nvar RegistryClient = require('bower-registry-client');\nvar registry = new RegistryClient(options, logger);\n```\n\nThe `logger` is optional and is expected to be an instance of the bower [logger](https://github.com/bower/logger).   \nAvailable constructor options:\n\n- `cache`: the cache folder to use for some operations; using null will disable  persistent cache (defaults to OS temp folder)\n- `registry.search`: an array of registry search endpoints (defaults to the Bower server)\n- `registry.register`: the endpoint to use when registering packages (defaults to the Bower server)\n- `registry.publish`: the endpoint to use when publishing packages (defaults to the Bower server)\n- `ca.search`: an array of CA certificates for each registry.search (defaults to null).\n- `ca.register`: the CA certificate for registry.register\n- `ca.publish`: the CA certificate for registry.publish\n- `proxy`: the proxy to use for http requests (defaults to null)\n- `httpsProxy`: the proxy to use for https requests (defaults to null)\n- `strictSsl`: whether or not to do SSL key validation when making requests via https (defaults to true).\n- `userAgent`: the user agent to use for the requests (defaults to null)\n- `timeout`: the timeout for the requests to finish (defaults to 60000)\n- `force`: If set to true, cache will be bypassed and remotes will always be hit (defaults to false).\n- `offline`: If set to true, only the cache will be used (defaults to false).\n\n\nNote that `force` and `offline` are mutually exclusive.\nThe cache will speedup operations such as `list`, `lookup` and `search`.\nDifferent operations may have different cache expiration times.\n\n\n#### .lookup(name, callback)\n\nLooks the registry for the package `name`,\n\n```js\nregistry.lookup('jquery', function (err, entry) {\n    if (err) {\n        console.error(err.message);\n        return;\n    }\n\n    // For now resp.type is always 'alias'\n    console.log('type', entry.type);\n    console.log('url', entry.url);\n});\n```\n\n#### .register(name, url, callback)\n\nRegisters a package in the registry.\n\n```js\nregistry.register('my-package', 'git://github.com/my-org/my-package.git', function (err, pkg) {\n    if (err) {\n        console.error(err.message);\n        return;\n    }\n\n    console.log('name', pkg.name);\n    console.log('url: ', pkg.url);\n});\n```\n\n#### .search(str, callback)\n\nSearches the registry.\n\n```js\nregistry.search('jquery', function (err, results) {\n    if (err) {\n        console.error(err.message);\n        return;\n    }\n\n    results.forEach(function (pkg) {\n        console.log('name', pkg.name);\n        console.log('url', pkg.url);\n    });\n});\n```\n\n#### .clearCache(name, callback)\n\nClears the persistent and runtime cache associated with the `name` package.   \nIf `name` is null, clears the cache for every package.\n\nNote that in most cases, you don't need to clear the cache since it has\nself expiration times.\n\n```js\n// Clear jquery cache\nregistry.clearCache('jquery', function (err) {\n    if (err) {\n        console.error(err.message);\n        return;\n    }\n\n    console.log('Done');\n});\n\n// Clear all cache\nregistry.clearCache(function (err) {\n    if (err) {\n        console.error(err.message);\n        return;\n    }\n\n    console.log('Done');\n});\n```\n\n\n#### .resetCache()\n\nClears the in-memory cache used to speed up the instance.\n\nNote that in most cases, you don't need to clear the runtime cache since it has\nself expiration times.\nMight be useful if you use this module in long-living programs.\n\n```js\nregistry.resetCache();\n```\n\n#### #clearRuntimeCache()\n\nClears the in-memory cache used to speed up the whole module.\nThis clears the static in-memory cache as well as in-memory cache used by instances.\n\nNote that in edge cases, some instance's in-memory cache might be skipped.\nIf that's a problem, you should create fresh instances instead.\n\n```js\nRegistryClient.clearRuntimeCache();\n```\n\n\n\n## License\n\nReleased under the [MIT License](http://www.opensource.org/licenses/mit-license.php).\n","readmeFilename":"README.md","bugs":{"url":"https://github.com/bower/registry-client/issues"},"_id":"bower-registry-client@0.1.0-rc.5","dist":{"shasum":"db0b495980a7fa52831394126470653337e23736","tarball":"http://registry.npmjs.org/bower-registry-client/-/bower-registry-client-0.1.0-rc.5.tgz"},"_from":".","_npmVersion":"1.3.2","_npmUser":{"name":"satazor","email":"andremiguelcruz@msn.com"},"maintainers":[{"name":"satazor","email":"andremiguelcruz@msn.com"}],"directories":{}},"0.1.0":{"name":"bower-registry-client","version":"0.1.0","description":"Provides easy interaction with the Bower registry.","author":{"name":"Twitter"},"licenses":[{"type":"MIT","url":"https://github.com/bower/registry-client/blob/master/LICENSE"}],"repository":{"type":"git","url":"git://github.com/bower/registry-client.git"},"main":"Client","engines":{"node":">=0.8.0"},"dependencies":{"async":"~0.2.8","deep-extend":"~0.2.5","graceful-fs":"~2.0.0","lru-cache":"~2.3.0","request":"~2.22.0","request-replay":"~0.1.0","rimraf":"~2.2.0","mkdirp":"~0.3.5"},"devDependencies":{"expect.js":"~0.2.0","grunt":"~0.4.1","grunt-contrib-watch":"~0.5.0","grunt-contrib-jshint":"~0.6.0","grunt-simple-mocha":"~0.4.0","mocha":"~1.12.0","nock":"~0.22.0"},"scripts":{"test":"grunt test"},"readme":"# bower-registry-client [![Build Status](https://secure.travis-ci.org/bower/registry-client.png?branch=master)](http://travis-ci.org/bower/registry-client)\n\nThis module allows you to easily interact with the Bower server API.\n\n\n## Usage\n\n```js\n\nvar RegistryClient = require('bower-registry-client');\nvar registry = new RegistryClient(options, logger);\n```\n\nThe `logger` is optional and is expected to be an instance of the bower [logger](https://github.com/bower/logger).   \nAvailable constructor options:\n\n- `cache`: the cache folder to use for some operations; using null will disable  persistent cache (defaults to OS temp folder)\n- `registry.search`: an array of registry search endpoints (defaults to the Bower server)\n- `registry.register`: the endpoint to use when registering packages (defaults to the Bower server)\n- `registry.publish`: the endpoint to use when publishing packages (defaults to the Bower server)\n- `ca.search`: an array of CA certificates for each registry.search (defaults to null).\n- `ca.register`: the CA certificate for registry.register\n- `ca.publish`: the CA certificate for registry.publish\n- `proxy`: the proxy to use for http requests (defaults to null)\n- `httpsProxy`: the proxy to use for https requests (defaults to null)\n- `strictSsl`: whether or not to do SSL key validation when making requests via https (defaults to true).\n- `userAgent`: the user agent to use for the requests (defaults to null)\n- `timeout`: the timeout for the requests to finish (defaults to 60000)\n- `force`: If set to true, cache will be bypassed and remotes will always be hit (defaults to false).\n- `offline`: If set to true, only the cache will be used (defaults to false).\n\n\nNote that `force` and `offline` are mutually exclusive.\nThe cache will speedup operations such as `list`, `lookup` and `search`.\nDifferent operations may have different cache expiration times.\n\n\n#### .lookup(name, callback)\n\nLooks the registry for the package `name`,\n\n```js\nregistry.lookup('jquery', function (err, entry) {\n    if (err) {\n        console.error(err.message);\n        return;\n    }\n\n    // For now resp.type is always 'alias'\n    console.log('type', entry.type);\n    console.log('url', entry.url);\n});\n```\n\n#### .register(name, url, callback)\n\nRegisters a package in the registry.\n\n```js\nregistry.register('my-package', 'git://github.com/my-org/my-package.git', function (err, pkg) {\n    if (err) {\n        console.error(err.message);\n        return;\n    }\n\n    console.log('name', pkg.name);\n    console.log('url: ', pkg.url);\n});\n```\n\n#### .search(str, callback)\n\nSearches the registry.\n\n```js\nregistry.search('jquery', function (err, results) {\n    if (err) {\n        console.error(err.message);\n        return;\n    }\n\n    results.forEach(function (pkg) {\n        console.log('name', pkg.name);\n        console.log('url', pkg.url);\n    });\n});\n```\n\n#### .clearCache(name, callback)\n\nClears the persistent and runtime cache associated with the `name` package.   \nIf `name` is null, clears the cache for every package.\n\nNote that in most cases, you don't need to clear the cache since it has\nself expiration times.\n\n```js\n// Clear jquery cache\nregistry.clearCache('jquery', function (err) {\n    if (err) {\n        console.error(err.message);\n        return;\n    }\n\n    console.log('Done');\n});\n\n// Clear all cache\nregistry.clearCache(function (err) {\n    if (err) {\n        console.error(err.message);\n        return;\n    }\n\n    console.log('Done');\n});\n```\n\n\n#### .resetCache()\n\nClears the in-memory cache used to speed up the instance.\n\nNote that in most cases, you don't need to clear the runtime cache since it has\nself expiration times.\nMight be useful if you use this module in long-living programs.\n\n```js\nregistry.resetCache();\n```\n\n#### #clearRuntimeCache()\n\nClears the in-memory cache used to speed up the whole module.\nThis clears the static in-memory cache as well as in-memory cache used by instances.\n\nNote that in edge cases, some instance's in-memory cache might be skipped.\nIf that's a problem, you should create fresh instances instead.\n\n```js\nRegistryClient.clearRuntimeCache();\n```\n\n\n\n## License\n\nReleased under the [MIT License](http://www.opensource.org/licenses/mit-license.php).\n","readmeFilename":"README.md","bugs":{"url":"https://github.com/bower/registry-client/issues"},"_id":"bower-registry-client@0.1.0","dist":{"shasum":"9bedee917c2203df8054e7995954a4bd0b7088d6","tarball":"http://registry.npmjs.org/bower-registry-client/-/bower-registry-client-0.1.0.tgz"},"_from":".","_npmVersion":"1.3.2","_npmUser":{"name":"satazor","email":"andremiguelcruz@msn.com"},"maintainers":[{"name":"satazor","email":"andremiguelcruz@msn.com"}],"directories":{}},"0.1.1":{"name":"bower-registry-client","version":"0.1.1","description":"Provides easy interaction with the Bower registry.","author":{"name":"Twitter"},"licenses":[{"type":"MIT","url":"https://github.com/bower/registry-client/blob/master/LICENSE"}],"repository":{"type":"git","url":"git://github.com/bower/registry-client.git"},"main":"Client","engines":{"node":">=0.8.0"},"dependencies":{"async":"~0.2.8","bower-config":"~0.2.0-rc.1","graceful-fs":"~2.0.0","lru-cache":"~2.3.0","request":"~2.25.0","request-replay":"~0.1.0","rimraf":"~2.2.0","mkdirp":"~0.3.5"},"devDependencies":{"expect.js":"~0.2.0","grunt":"~0.4.1","grunt-contrib-watch":"~0.5.0","grunt-contrib-jshint":"~0.6.0","grunt-simple-mocha":"~0.4.0","mocha":"~1.12.0","nock":"~0.22.0"},"scripts":{"test":"grunt test"},"readme":"# bower-registry-client [![Build Status](https://secure.travis-ci.org/bower/registry-client.png?branch=master)](http://travis-ci.org/bower/registry-client)\n\nThis module allows you to easily interact with the Bower server API.\n\n\n## Usage\n\n```js\n\nvar RegistryClient = require('bower-registry-client');\nvar registry = new RegistryClient(options, logger);\n```\n\nThe `logger` is optional and is expected to be an instance of the bower [logger](https://github.com/bower/logger).   \nAvailable constructor options:\n\n- `cache`: the cache folder to use for some operations; using null will disable persistent cache (defaults to bower registry cache folder)\n- `registry.search`: an array of registry search endpoints (defaults to the Bower server)\n- `registry.register`: the endpoint to use when registering packages (defaults to the Bower server)\n- `registry.publish`: the endpoint to use when publishing packages (defaults to the Bower server)\n- `ca.search`: an array of CA certificates for each registry.search (defaults to null).\n- `ca.register`: the CA certificate for registry.register\n- `ca.publish`: the CA certificate for registry.publish\n- `proxy`: the proxy to use for http requests (defaults to null)\n- `httpsProxy`: the proxy to use for https requests (defaults to null)\n- `strictSsl`: whether or not to do SSL key validation when making requests via https (defaults to true).\n- `userAgent`: the user agent to use for the requests (defaults to null)\n- `timeout`: the timeout for the requests to finish (defaults to 60000)\n- `force`: If set to true, cache will be bypassed and remotes will always be hit (defaults to false).\n- `offline`: If set to true, only the cache will be used (defaults to false).\n\n\nNote that `force` and `offline` are mutually exclusive.\nThe cache will speedup operations such as `list`, `lookup` and `search`.\nDifferent operations may have different cache expiration times.\n\n\n#### .lookup(name, callback)\n\nLooks the registry for the package `name`,\n\n```js\nregistry.lookup('jquery', function (err, entry) {\n    if (err) {\n        console.error(err.message);\n        return;\n    }\n\n    // For now resp.type is always 'alias'\n    console.log('type', entry.type);\n    console.log('url', entry.url);\n});\n```\n\n#### .register(name, url, callback)\n\nRegisters a package in the registry.\n\n```js\nregistry.register('my-package', 'git://github.com/my-org/my-package.git', function (err, pkg) {\n    if (err) {\n        console.error(err.message);\n        return;\n    }\n\n    console.log('name', pkg.name);\n    console.log('url: ', pkg.url);\n});\n```\n\n#### .search(str, callback)\n\nSearches the registry.\n\n```js\nregistry.search('jquery', function (err, results) {\n    if (err) {\n        console.error(err.message);\n        return;\n    }\n\n    results.forEach(function (pkg) {\n        console.log('name', pkg.name);\n        console.log('url', pkg.url);\n    });\n});\n```\n\n#### .clearCache(name, callback)\n\nClears the persistent and runtime cache associated with the `name` package.   \nIf `name` is null, clears the cache for every package.\n\nNote that in most cases, you don't need to clear the cache since it has\nself expiration times.\n\n```js\n// Clear jquery cache\nregistry.clearCache('jquery', function (err) {\n    if (err) {\n        console.error(err.message);\n        return;\n    }\n\n    console.log('Done');\n});\n\n// Clear all cache\nregistry.clearCache(function (err) {\n    if (err) {\n        console.error(err.message);\n        return;\n    }\n\n    console.log('Done');\n});\n```\n\n\n#### .resetCache()\n\nClears the in-memory cache used to speed up the instance.\n\nNote that in most cases, you don't need to clear the runtime cache since it has\nself expiration times.\nMight be useful if you use this module in long-living programs.\n\n```js\nregistry.resetCache();\n```\n\n#### #clearRuntimeCache()\n\nClears the in-memory cache used to speed up the whole module.\nThis clears the static in-memory cache as well as in-memory cache used by instances.\n\nNote that in edge cases, some instance's in-memory cache might be skipped.\nIf that's a problem, you should create fresh instances instead.\n\n```js\nRegistryClient.clearRuntimeCache();\n```\n\n\n\n## License\n\nReleased under the [MIT License](http://www.opensource.org/licenses/mit-license.php).\n","readmeFilename":"README.md","bugs":{"url":"https://github.com/bower/registry-client/issues"},"_id":"bower-registry-client@0.1.1","dist":{"shasum":"6cbdcf286340a0f395b33332cdeb8cec06868e0f","tarball":"http://registry.npmjs.org/bower-registry-client/-/bower-registry-client-0.1.1.tgz"},"_from":".","_npmVersion":"1.3.2","_npmUser":{"name":"satazor","email":"andremiguelcruz@msn.com"},"maintainers":[{"name":"satazor","email":"andremiguelcruz@msn.com"}],"directories":{}},"0.1.2":{"name":"bower-registry-client","version":"0.1.2","description":"Provides easy interaction with the Bower registry.","author":{"name":"Twitter"},"licenses":[{"type":"MIT","url":"https://github.com/bower/registry-client/blob/master/LICENSE"}],"repository":{"type":"git","url":"git://github.com/bower/registry-client.git"},"main":"Client","engines":{"node":">=0.8.0"},"dependencies":{"async":"~0.2.8","bower-config":"~0.2.0","graceful-fs":"~2.0.0","lru-cache":"~2.3.0","request":"~2.25.0","request-replay":"~0.2.0","rimraf":"~2.2.0","mkdirp":"~0.3.5"},"devDependencies":{"expect.js":"~0.2.0","grunt":"~0.4.1","grunt-contrib-watch":"~0.5.0","grunt-contrib-jshint":"~0.6.0","grunt-simple-mocha":"~0.4.0","mocha":"~1.12.0","nock":"~0.22.0"},"scripts":{"test":"grunt test"},"readme":"# bower-registry-client [![Build Status](https://secure.travis-ci.org/bower/registry-client.png?branch=master)](http://travis-ci.org/bower/registry-client)\n\nThis module allows you to easily interact with the Bower server API.\n\n\n## Usage\n\n```js\n\nvar RegistryClient = require('bower-registry-client');\nvar registry = new RegistryClient(options, logger);\n```\n\nThe `logger` is optional and is expected to be an instance of the bower [logger](https://github.com/bower/logger).   \nAvailable constructor options:\n\n- `cache`: the cache folder to use for some operations; using null will disable persistent cache (defaults to bower registry cache folder)\n- `registry.search`: an array of registry search endpoints (defaults to the Bower server)\n- `registry.register`: the endpoint to use when registering packages (defaults to the Bower server)\n- `registry.publish`: the endpoint to use when publishing packages (defaults to the Bower server)\n- `ca.search`: an array of CA certificates for each registry.search (defaults to null).\n- `ca.register`: the CA certificate for registry.register\n- `ca.publish`: the CA certificate for registry.publish\n- `proxy`: the proxy to use for http requests (defaults to null)\n- `httpsProxy`: the proxy to use for https requests (defaults to null)\n- `strictSsl`: whether or not to do SSL key validation when making requests via https (defaults to true).\n- `userAgent`: the user agent to use for the requests (defaults to null)\n- `timeout`: the timeout for the requests to finish (defaults to 60000)\n- `force`: If set to true, cache will be bypassed and remotes will always be hit (defaults to false).\n- `offline`: If set to true, only the cache will be used (defaults to false).\n\n\nNote that `force` and `offline` are mutually exclusive.\nThe cache will speedup operations such as `list`, `lookup` and `search`.\nDifferent operations may have different cache expiration times.\n\n\n#### .lookup(name, callback)\n\nLooks the registry for the package `name`,\n\n```js\nregistry.lookup('jquery', function (err, entry) {\n    if (err) {\n        console.error(err.message);\n        return;\n    }\n\n    // For now resp.type is always 'alias'\n    console.log('type', entry.type);\n    console.log('url', entry.url);\n});\n```\n\n#### .register(name, url, callback)\n\nRegisters a package in the registry.\n\n```js\nregistry.register('my-package', 'git://github.com/my-org/my-package.git', function (err, pkg) {\n    if (err) {\n        console.error(err.message);\n        return;\n    }\n\n    console.log('name', pkg.name);\n    console.log('url: ', pkg.url);\n});\n```\n\n#### .search(str, callback)\n\nSearches the registry.\n\n```js\nregistry.search('jquery', function (err, results) {\n    if (err) {\n        console.error(err.message);\n        return;\n    }\n\n    results.forEach(function (pkg) {\n        console.log('name', pkg.name);\n        console.log('url', pkg.url);\n    });\n});\n```\n\n#### .clearCache(name, callback)\n\nClears the persistent and runtime cache associated with the `name` package.   \nIf `name` is null, clears the cache for every package.\n\nNote that in most cases, you don't need to clear the cache since it has\nself expiration times.\n\n```js\n// Clear jquery cache\nregistry.clearCache('jquery', function (err) {\n    if (err) {\n        console.error(err.message);\n        return;\n    }\n\n    console.log('Done');\n});\n\n// Clear all cache\nregistry.clearCache(function (err) {\n    if (err) {\n        console.error(err.message);\n        return;\n    }\n\n    console.log('Done');\n});\n```\n\n\n#### .resetCache()\n\nClears the in-memory cache used to speed up the instance.\n\nNote that in most cases, you don't need to clear the runtime cache since it has\nself expiration times.\nMight be useful if you use this module in long-living programs.\n\n```js\nregistry.resetCache();\n```\n\n#### #clearRuntimeCache()\n\nClears the in-memory cache used to speed up the whole module.\nThis clears the static in-memory cache as well as in-memory cache used by instances.\n\nNote that in edge cases, some instance's in-memory cache might be skipped.\nIf that's a problem, you should create fresh instances instead.\n\n```js\nRegistryClient.clearRuntimeCache();\n```\n\n\n\n## License\n\nReleased under the [MIT License](http://www.opensource.org/licenses/mit-license.php).\n","readmeFilename":"README.md","bugs":{"url":"https://github.com/bower/registry-client/issues"},"_id":"bower-registry-client@0.1.2","dist":{"shasum":"829150ee08fe682576615f615bfb9b6c776a1afb","tarball":"http://registry.npmjs.org/bower-registry-client/-/bower-registry-client-0.1.2.tgz"},"_from":".","_npmVersion":"1.3.2","_npmUser":{"name":"satazor","email":"andremiguelcruz@msn.com"},"maintainers":[{"name":"satazor","email":"andremiguelcruz@msn.com"}],"directories":{}},"0.1.3":{"name":"bower-registry-client","version":"0.1.3","description":"Provides easy interaction with the Bower registry.","author":{"name":"Twitter"},"licenses":[{"type":"MIT","url":"https://github.com/bower/registry-client/blob/master/LICENSE"}],"repository":{"type":"git","url":"git://github.com/bower/registry-client.git"},"main":"Client","engines":{"node":">=0.8.0"},"dependencies":{"async":"~0.2.8","bower-config":"~0.2.0","graceful-fs":"~2.0.0","lru-cache":"~2.3.0","request":"~2.25.0","request-replay":"~0.2.0","rimraf":"~2.2.0","mkdirp":"~0.3.5"},"devDependencies":{"expect.js":"~0.2.0","grunt":"~0.4.1","grunt-contrib-watch":"~0.5.0","grunt-contrib-jshint":"~0.6.0","grunt-simple-mocha":"~0.4.0","mocha":"~1.12.0","nock":"~0.22.0"},"scripts":{"test":"grunt test"},"readme":"# bower-registry-client [![Build Status](https://secure.travis-ci.org/bower/registry-client.png?branch=master)](http://travis-ci.org/bower/registry-client)\n\nThis module allows you to easily interact with the Bower server API.\n\n\n## Usage\n\n```js\n\nvar RegistryClient = require('bower-registry-client');\nvar registry = new RegistryClient(options, logger);\n```\n\nThe `logger` is optional and is expected to be an instance of the bower [logger](https://github.com/bower/logger).   \nAvailable constructor options:\n\n- `cache`: the cache folder to use for some operations; using null will disable persistent cache (defaults to bower registry cache folder)\n- `registry.search`: an array of registry search endpoints (defaults to the Bower server)\n- `registry.register`: the endpoint to use when registering packages (defaults to the Bower server)\n- `registry.publish`: the endpoint to use when publishing packages (defaults to the Bower server)\n- `ca.search`: an array of CA certificates for each registry.search (defaults to null).\n- `ca.register`: the CA certificate for registry.register\n- `ca.publish`: the CA certificate for registry.publish\n- `proxy`: the proxy to use for http requests (defaults to null)\n- `httpsProxy`: the proxy to use for https requests (defaults to null)\n- `strictSsl`: whether or not to do SSL key validation when making requests via https (defaults to true).\n- `userAgent`: the user agent to use for the requests (defaults to null)\n- `timeout`: the timeout for the requests to finish (defaults to 60000)\n- `force`: If set to true, cache will be bypassed and remotes will always be hit (defaults to false).\n- `offline`: If set to true, only the cache will be used (defaults to false).\n\n\nNote that `force` and `offline` are mutually exclusive.\nThe cache will speedup operations such as `list`, `lookup` and `search`.\nDifferent operations may have different cache expiration times.\n\n\n#### .lookup(name, callback)\n\nLooks the registry for the package `name`,\n\n```js\nregistry.lookup('jquery', function (err, entry) {\n    if (err) {\n        console.error(err.message);\n        return;\n    }\n\n    // For now resp.type is always 'alias'\n    console.log('type', entry.type);\n    console.log('url', entry.url);\n});\n```\n\n#### .register(name, url, callback)\n\nRegisters a package in the registry.\n\n```js\nregistry.register('my-package', 'git://github.com/my-org/my-package.git', function (err, pkg) {\n    if (err) {\n        console.error(err.message);\n        return;\n    }\n\n    console.log('name', pkg.name);\n    console.log('url: ', pkg.url);\n});\n```\n\n#### .search(str, callback)\n\nSearches the registry.\n\n```js\nregistry.search('jquery', function (err, results) {\n    if (err) {\n        console.error(err.message);\n        return;\n    }\n\n    results.forEach(function (pkg) {\n        console.log('name', pkg.name);\n        console.log('url', pkg.url);\n    });\n});\n```\n\n#### .clearCache(name, callback)\n\nClears the persistent and runtime cache associated with the `name` package.   \nIf `name` is null, clears the cache for every package.\n\nNote that in most cases, you don't need to clear the cache since it has\nself expiration times.\n\n```js\n// Clear jquery cache\nregistry.clearCache('jquery', function (err) {\n    if (err) {\n        console.error(err.message);\n        return;\n    }\n\n    console.log('Done');\n});\n\n// Clear all cache\nregistry.clearCache(function (err) {\n    if (err) {\n        console.error(err.message);\n        return;\n    }\n\n    console.log('Done');\n});\n```\n\n\n#### .resetCache()\n\nClears the in-memory cache used to speed up the instance.\n\nNote that in most cases, you don't need to clear the runtime cache since it has\nself expiration times.\nMight be useful if you use this module in long-living programs.\n\n```js\nregistry.resetCache();\n```\n\n#### #clearRuntimeCache()\n\nClears the in-memory cache used to speed up the whole module.\nThis clears the static in-memory cache as well as in-memory cache used by instances.\n\nNote that in edge cases, some instance's in-memory cache might be skipped.\nIf that's a problem, you should create fresh instances instead.\n\n```js\nRegistryClient.clearRuntimeCache();\n```\n\n\n\n## License\n\nReleased under the [MIT License](http://www.opensource.org/licenses/mit-license.php).\n","readmeFilename":"README.md","bugs":{"url":"https://github.com/bower/registry-client/issues"},"_id":"bower-registry-client@0.1.3","dist":{"shasum":"eb168dc977d5967cd18acccd14f2718c63e17e11","tarball":"http://registry.npmjs.org/bower-registry-client/-/bower-registry-client-0.1.3.tgz"},"_from":".","_npmVersion":"1.3.2","_npmUser":{"name":"satazor","email":"andremiguelcruz@msn.com"},"maintainers":[{"name":"satazor","email":"andremiguelcruz@msn.com"}],"directories":{}},"0.1.4":{"name":"bower-registry-client","version":"0.1.4","description":"Provides easy interaction with the Bower registry.","author":{"name":"Twitter"},"licenses":[{"type":"MIT","url":"https://github.com/bower/registry-client/blob/master/LICENSE"}],"repository":{"type":"git","url":"git://github.com/bower/registry-client.git"},"main":"Client","engines":{"node":">=0.8.0"},"dependencies":{"async":"~0.2.8","bower-config":"~0.4.3","graceful-fs":"~2.0.0","lru-cache":"~2.3.0","request":"~2.27.0","request-replay":"~0.2.0","rimraf":"~2.2.0","mkdirp":"~0.3.5"},"devDependencies":{"expect.js":"~0.2.0","grunt":"~0.4.1","grunt-contrib-watch":"~0.5.0","grunt-contrib-jshint":"~0.6.0","grunt-simple-mocha":"~0.4.0","mocha":"~1.12.0","nock":"~0.22.0"},"scripts":{"test":"grunt test"},"readme":"# bower-registry-client [![Build Status](https://secure.travis-ci.org/bower/registry-client.png?branch=master)](http://travis-ci.org/bower/registry-client)\n\nThis module allows you to easily interact with the Bower server API.\n\n\n## Usage\n\n```js\n\nvar RegistryClient = require('bower-registry-client');\nvar registry = new RegistryClient(options, logger);\n```\n\nThe `logger` is optional and is expected to be an instance of the bower [logger](https://github.com/bower/logger).   \nAvailable constructor options:\n\n- `cache`: the cache folder to use for some operations; using null will disable persistent cache (defaults to bower registry cache folder)\n- `registry.search`: an array of registry search endpoints (defaults to the Bower server)\n- `registry.register`: the endpoint to use when registering packages (defaults to the Bower server)\n- `registry.publish`: the endpoint to use when publishing packages (defaults to the Bower server)\n- `ca.search`: an array of CA certificates for each registry.search (defaults to null).\n- `ca.register`: the CA certificate for registry.register\n- `ca.publish`: the CA certificate for registry.publish\n- `proxy`: the proxy to use for http requests (defaults to null)\n- `httpsProxy`: the proxy to use for https requests (defaults to null)\n- `strictSsl`: whether or not to do SSL key validation when making requests via https (defaults to true).\n- `userAgent`: the user agent to use for the requests (defaults to null)\n- `timeout`: the timeout for the requests to finish (defaults to 60000)\n- `force`: If set to true, cache will be bypassed and remotes will always be hit (defaults to false).\n- `offline`: If set to true, only the cache will be used (defaults to false).\n\n\nNote that `force` and `offline` are mutually exclusive.\nThe cache will speedup operations such as `list`, `lookup` and `search`.\nDifferent operations may have different cache expiration times.\n\n\n#### .lookup(name, callback)\n\nLooks the registry for the package `name`,\n\n```js\nregistry.lookup('jquery', function (err, entry) {\n    if (err) {\n        console.error(err.message);\n        return;\n    }\n\n    // For now resp.type is always 'alias'\n    console.log('type', entry.type);\n    console.log('url', entry.url);\n});\n```\n\n#### .register(name, url, callback)\n\nRegisters a package in the registry.\n\n```js\nregistry.register('my-package', 'git://github.com/my-org/my-package.git', function (err, pkg) {\n    if (err) {\n        console.error(err.message);\n        return;\n    }\n\n    console.log('name', pkg.name);\n    console.log('url: ', pkg.url);\n});\n```\n\n#### .search(str, callback)\n\nSearches the registry.\n\n```js\nregistry.search('jquery', function (err, results) {\n    if (err) {\n        console.error(err.message);\n        return;\n    }\n\n    results.forEach(function (pkg) {\n        console.log('name', pkg.name);\n        console.log('url', pkg.url);\n    });\n});\n```\n\n#### .clearCache(name, callback)\n\nClears the persistent and runtime cache associated with the `name` package.   \nIf `name` is null, clears the cache for every package.\n\nNote that in most cases, you don't need to clear the cache since it has\nself expiration times.\n\n```js\n// Clear jquery cache\nregistry.clearCache('jquery', function (err) {\n    if (err) {\n        console.error(err.message);\n        return;\n    }\n\n    console.log('Done');\n});\n\n// Clear all cache\nregistry.clearCache(function (err) {\n    if (err) {\n        console.error(err.message);\n        return;\n    }\n\n    console.log('Done');\n});\n```\n\n\n#### .resetCache()\n\nClears the in-memory cache used to speed up the instance.\n\nNote that in most cases, you don't need to clear the runtime cache since it has\nself expiration times.\nMight be useful if you use this module in long-living programs.\n\n```js\nregistry.resetCache();\n```\n\n#### #clearRuntimeCache()\n\nClears the in-memory cache used to speed up the whole module.\nThis clears the static in-memory cache as well as in-memory cache used by instances.\n\nNote that in edge cases, some instance's in-memory cache might be skipped.\nIf that's a problem, you should create fresh instances instead.\n\n```js\nRegistryClient.clearRuntimeCache();\n```\n\n\n\n## License\n\nReleased under the [MIT License](http://www.opensource.org/licenses/mit-license.php).\n","readmeFilename":"README.md","bugs":{"url":"https://github.com/bower/registry-client/issues"},"_id":"bower-registry-client@0.1.4","dist":{"shasum":"334669747ca0b60fdda24b0de1f4c3057429813c","tarball":"http://registry.npmjs.org/bower-registry-client/-/bower-registry-client-0.1.4.tgz"},"_from":".","_npmVersion":"1.3.2","_npmUser":{"name":"satazor","email":"andremiguelcruz@msn.com"},"maintainers":[{"name":"satazor","email":"andremiguelcruz@msn.com"}],"directories":{}},"0.1.5":{"name":"bower-registry-client","version":"0.1.5","description":"Provides easy interaction with the Bower registry.","author":{"name":"Twitter"},"licenses":[{"type":"MIT","url":"https://github.com/bower/registry-client/blob/master/LICENSE"}],"repository":{"type":"git","url":"git://github.com/bower/registry-client.git"},"main":"Client","engines":{"node":">=0.8.0"},"dependencies":{"async":"~0.2.8","bower-config":"~0.4.3","graceful-fs":"~2.0.0","lru-cache":"~2.3.0","request":"~2.27.0","request-replay":"~0.2.0","rimraf":"~2.2.0","mkdirp":"~0.3.5"},"devDependencies":{"expect.js":"~0.2.0","grunt":"~0.4.1","grunt-contrib-watch":"~0.5.0","grunt-contrib-jshint":"~0.6.0","grunt-simple-mocha":"~0.4.0","mocha":"~1.12.0","nock":"~0.22.0"},"scripts":{"test":"grunt test"},"readme":"# bower-registry-client [![Build Status](https://secure.travis-ci.org/bower/registry-client.png?branch=master)](http://travis-ci.org/bower/registry-client)\n\nThis module allows you to easily interact with the Bower server API.\n\n\n## Usage\n\n```js\n\nvar RegistryClient = require('bower-registry-client');\nvar registry = new RegistryClient(options, logger);\n```\n\nThe `logger` is optional and is expected to be an instance of the bower [logger](https://github.com/bower/logger).   \nAvailable constructor options:\n\n- `cache`: the cache folder to use for some operations; using null will disable persistent cache (defaults to bower registry cache folder)\n- `registry.search`: an array of registry search endpoints (defaults to the Bower server)\n- `registry.register`: the endpoint to use when registering packages (defaults to the Bower server)\n- `registry.publish`: the endpoint to use when publishing packages (defaults to the Bower server)\n- `ca.search`: an array of CA certificates for each registry.search (defaults to null).\n- `ca.register`: the CA certificate for registry.register\n- `ca.publish`: the CA certificate for registry.publish\n- `proxy`: the proxy to use for http requests (defaults to null)\n- `httpsProxy`: the proxy to use for https requests (defaults to null)\n- `strictSsl`: whether or not to do SSL key validation when making requests via https (defaults to true).\n- `userAgent`: the user agent to use for the requests (defaults to null)\n- `timeout`: the timeout for the requests to finish (defaults to 60000)\n- `force`: If set to true, cache will be bypassed and remotes will always be hit (defaults to false).\n- `offline`: If set to true, only the cache will be used (defaults to false).\n\n\nNote that `force` and `offline` are mutually exclusive.\nThe cache will speedup operations such as `list`, `lookup` and `search`.\nDifferent operations may have different cache expiration times.\n\n\n#### .lookup(name, callback)\n\nLooks the registry for the package `name`,\n\n```js\nregistry.lookup('jquery', function (err, entry) {\n    if (err) {\n        console.error(err.message);\n        return;\n    }\n\n    // For now resp.type is always 'alias'\n    console.log('type', entry.type);\n    console.log('url', entry.url);\n});\n```\n\n#### .register(name, url, callback)\n\nRegisters a package in the registry.\n\n```js\nregistry.register('my-package', 'git://github.com/my-org/my-package.git', function (err, pkg) {\n    if (err) {\n        console.error(err.message);\n        return;\n    }\n\n    console.log('name', pkg.name);\n    console.log('url: ', pkg.url);\n});\n```\n\n#### .search(str, callback)\n\nSearches the registry.\n\n```js\nregistry.search('jquery', function (err, results) {\n    if (err) {\n        console.error(err.message);\n        return;\n    }\n\n    results.forEach(function (pkg) {\n        console.log('name', pkg.name);\n        console.log('url', pkg.url);\n    });\n});\n```\n\n#### .clearCache(name, callback)\n\nClears the persistent and runtime cache associated with the `name` package.   \nIf `name` is null, clears the cache for every package.\n\nNote that in most cases, you don't need to clear the cache since it has\nself expiration times.\n\n```js\n// Clear jquery cache\nregistry.clearCache('jquery', function (err) {\n    if (err) {\n        console.error(err.message);\n        return;\n    }\n\n    console.log('Done');\n});\n\n// Clear all cache\nregistry.clearCache(function (err) {\n    if (err) {\n        console.error(err.message);\n        return;\n    }\n\n    console.log('Done');\n});\n```\n\n\n#### .resetCache()\n\nClears the in-memory cache used to speed up the instance.\n\nNote that in most cases, you don't need to clear the runtime cache since it has\nself expiration times.\nMight be useful if you use this module in long-living programs.\n\n```js\nregistry.resetCache();\n```\n\n#### #clearRuntimeCache()\n\nClears the in-memory cache used to speed up the whole module.\nThis clears the static in-memory cache as well as in-memory cache used by instances.\n\nNote that in edge cases, some instance's in-memory cache might be skipped.\nIf that's a problem, you should create fresh instances instead.\n\n```js\nRegistryClient.clearRuntimeCache();\n```\n\n\n\n## License\n\nReleased under the [MIT License](http://www.opensource.org/licenses/mit-license.php).\n","readmeFilename":"README.md","bugs":{"url":"https://github.com/bower/registry-client/issues"},"_id":"bower-registry-client@0.1.5","dist":{"shasum":"1c64d70bfca833c95121ffc23da48a54527912d3","tarball":"http://registry.npmjs.org/bower-registry-client/-/bower-registry-client-0.1.5.tgz"},"_from":".","_npmVersion":"1.3.5","_npmUser":{"name":"satazor","email":"andremiguelcruz@msn.com"},"maintainers":[{"name":"satazor","email":"andremiguelcruz@msn.com"}],"directories":{}},"0.1.6":{"name":"bower-registry-client","version":"0.1.6","description":"Provides easy interaction with the Bower registry.","author":{"name":"Twitter"},"licenses":[{"type":"MIT","url":"https://github.com/bower/registry-client/blob/master/LICENSE"}],"repository":{"type":"git","url":"git://github.com/bower/registry-client.git"},"main":"Client","engines":{"node":">=0.8.0"},"dependencies":{"async":"~0.2.8","bower-config":"~0.4.3","graceful-fs":"~2.0.0","lru-cache":"~2.3.0","request":"~2.27.0","request-replay":"~0.2.0","rimraf":"~2.2.0","mkdirp":"~0.3.5"},"devDependencies":{"expect.js":"~0.2.0","grunt":"~0.4.1","grunt-contrib-watch":"~0.5.0","grunt-contrib-jshint":"~0.6.0","grunt-simple-mocha":"~0.4.0","mocha":"~1.12.0","nock":"~0.22.0"},"scripts":{"test":"grunt test"},"readme":"# bower-registry-client [![Build Status](https://secure.travis-ci.org/bower/registry-client.png?branch=master)](http://travis-ci.org/bower/registry-client)\n\nThis module allows you to easily interact with the Bower server API.\n\n\n## Usage\n\n```js\n\nvar RegistryClient = require('bower-registry-client');\nvar registry = new RegistryClient(options, logger);\n```\n\nThe `logger` is optional and is expected to be an instance of the bower [logger](https://github.com/bower/logger).   \nAvailable constructor options:\n\n- `cache`: the cache folder to use for some operations; using null will disable persistent cache (defaults to bower registry cache folder)\n- `registry.search`: an array of registry search endpoints (defaults to the Bower server)\n- `registry.register`: the endpoint to use when registering packages (defaults to the Bower server)\n- `registry.publish`: the endpoint to use when publishing packages (defaults to the Bower server)\n- `ca.search`: an array of CA certificates for each registry.search (defaults to null).\n- `ca.register`: the CA certificate for registry.register\n- `ca.publish`: the CA certificate for registry.publish\n- `proxy`: the proxy to use for http requests (defaults to null)\n- `httpsProxy`: the proxy to use for https requests (defaults to null)\n- `strictSsl`: whether or not to do SSL key validation when making requests via https (defaults to true).\n- `userAgent`: the user agent to use for the requests (defaults to null)\n- `timeout`: the timeout for the requests to finish (defaults to 60000)\n- `force`: If set to true, cache will be bypassed and remotes will always be hit (defaults to false).\n- `offline`: If set to true, only the cache will be used (defaults to false).\n\n\nNote that `force` and `offline` are mutually exclusive.\nThe cache will speedup operations such as `list`, `lookup` and `search`.\nDifferent operations may have different cache expiration times.\n\n\n#### .lookup(name, callback)\n\nLooks the registry for the package `name`,\n\n```js\nregistry.lookup('jquery', function (err, entry) {\n    if (err) {\n        console.error(err.message);\n        return;\n    }\n\n    // For now resp.type is always 'alias'\n    console.log('type', entry.type);\n    console.log('url', entry.url);\n});\n```\n\n#### .register(name, url, callback)\n\nRegisters a package in the registry.\n\n```js\nregistry.register('my-package', 'git://github.com/my-org/my-package.git', function (err, pkg) {\n    if (err) {\n        console.error(err.message);\n        return;\n    }\n\n    console.log('name', pkg.name);\n    console.log('url: ', pkg.url);\n});\n```\n\n#### .search(str, callback)\n\nSearches the registry.\n\n```js\nregistry.search('jquery', function (err, results) {\n    if (err) {\n        console.error(err.message);\n        return;\n    }\n\n    results.forEach(function (pkg) {\n        console.log('name', pkg.name);\n        console.log('url', pkg.url);\n    });\n});\n```\n\n#### .clearCache(name, callback)\n\nClears the persistent and runtime cache associated with the `name` package.   \nIf `name` is null, clears the cache for every package.\n\nNote that in most cases, you don't need to clear the cache since it has\nself expiration times.\n\n```js\n// Clear jquery cache\nregistry.clearCache('jquery', function (err) {\n    if (err) {\n        console.error(err.message);\n        return;\n    }\n\n    console.log('Done');\n});\n\n// Clear all cache\nregistry.clearCache(function (err) {\n    if (err) {\n        console.error(err.message);\n        return;\n    }\n\n    console.log('Done');\n});\n```\n\n\n#### .resetCache()\n\nClears the in-memory cache used to speed up the instance.\n\nNote that in most cases, you don't need to clear the runtime cache since it has\nself expiration times.\nMight be useful if you use this module in long-living programs.\n\n```js\nregistry.resetCache();\n```\n\n#### #clearRuntimeCache()\n\nClears the in-memory cache used to speed up the whole module.\nThis clears the static in-memory cache as well as in-memory cache used by instances.\n\nNote that in edge cases, some instance's in-memory cache might be skipped.\nIf that's a problem, you should create fresh instances instead.\n\n```js\nRegistryClient.clearRuntimeCache();\n```\n\n\n\n## License\n\nReleased under the [MIT License](http://www.opensource.org/licenses/mit-license.php).\n","readmeFilename":"README.md","bugs":{"url":"https://github.com/bower/registry-client/issues"},"_id":"bower-registry-client@0.1.6","dist":{"shasum":"c3ae74a98f24f50a373bbcb0ef443558be01d4b7","tarball":"http://registry.npmjs.org/bower-registry-client/-/bower-registry-client-0.1.6.tgz"},"_from":".","_npmVersion":"1.3.11","_npmUser":{"name":"svnlto","email":"me@svenlito.com"},"maintainers":[{"name":"satazor","email":"andremiguelcruz@msn.com"},{"name":"svnlto","email":"me@svenlito.com"}],"directories":{}}},"readme":"# bower-registry-client [![Build Status](https://secure.travis-ci.org/bower/registry-client.png?branch=master)](http://travis-ci.org/bower/registry-client)\n\nThis module allows you to easily interact with the Bower server API.\n\n\n## Usage\n\n```js\n\nvar RegistryClient = require('bower-registry-client');\nvar registry = new RegistryClient(options);\n```\n\nAvailable constructor options:\n\n- `cache`: the cache folder to use for some operations; using null will disable  persistent cache (defaults to OS temp folder)\n- `registry.search`: an array of registry search endpoints (defaults to the Bower server)\n- `registry.register`: the endpoint to use when registering packages (defaults to the Bower server)\n- `registry.publish`: the endpoint to use when publishing packages (defaults to the Bower server)\n- `ca.search`: an array of CA certificates for each registry.search (defaults to null).\n- `ca.register`: the CA certificate for registry.register\n- `ca.publish`: the CA certificate for registry.publish\n- `proxy`: the proxy to use for http requests (defaults to null)\n- `httpsProxy`: the proxy to use for https requests (defaults to null)\n- `strictSsl`: whether or not to do SSL key validation when making requests via https (defaults to true).\n- `userAgent`: the user agent to use for the requests (defaults to null)\n- `timeout`: the timeout for the requests to finish (defaults to 5000)\n- `force`: If set to true, cache will be bypassed and remotes will always be hit (defaults to false).\n- `offline`: If set to true, only the cache will be used (defaults to false).\n\n\nNote that `force` and `offline` are mutually exclusive.\nThe cache will speedup operations such as `lookup` and `info`.\nDifferent operations may have different cache expiration times.\n\n\n#### .lookup(name, callback)\n\nLooks the registry for the package `name`,\n\n```js\nregistry.lookup('jquery', function (err, entry) {\n    if (err) {\n        console.error(err.message);\n        return;\n    }\n\n    // For now resp.type is always 'alias'\n    console.log('type', entry.type);\n    console.log('url', entry.url);\n});\n```\n\n#### .register(name, url, callback)\n\nRegisters a package in the registry.\n\n```js\nregistry.register('my-package', 'git://github.com/my-org/my-package.git', function (err, pkg) {\n    if (err) {\n        console.error(err.message);\n        return;\n    }\n\n    console.log('name', pkg.name);\n    console.log('url: ', pkg.url);\n});\n```\n\n#### .search(str, callback)\n\nSearches the registry.\n\n```js\nregistry.search('jquery', function (err, results) {\n    if (err) {\n        console.error(err.message);\n        return;\n    }\n\n    results.forEach(function (pkg) {\n        console.log('name', pkg.name);\n        console.log('url', pkg.url);\n    });\n});\n```\n\n#### .clearCache(name, callback)\n\nClears the persistent and runtime cache associated with the `name` package.   \nIf `name` is null, clears the cache for every package.\n\nNote that in most cases, you don't need to clear the cache since it has\nself expiration times.\n\n```js\n// Clear jquery cache\nregistry.clearCache('jquery', function (err) {\n    if (err) {\n        console.error(err.message);\n        return;\n    }\n\n    console.log('Done');\n});\n\n// Clear all cache\nregistry.clearCache(function (err) {\n    if (err) {\n        console.error(err.message);\n        return;\n    }\n\n    console.log('Done');\n});\n```\n\n\n#### .resetCache()\n\nClears the in-memory cache used to speed up the instance.\n\nNote that in most cases, you don't need to clear the runtime cache since it has\nself expiration times.\nMight be useful if you use this module in long-living programs.\n\n```js\nregistry.resetCache();\n```\n\n#### #clearRuntimeCache()\n\nClears the in-memory cache used to speed up the whole module.\nThis clears the static in-memory cache as well as in-memory cache used by instances.\n\nNote that in edge cases, some instance's in-memory cache might be skipped.\nIf that's a problem, you should create fresh instances instead.\n\n```js\nRegistryClient.clearRuntimeCache();\n```\n\n\n\n## License\n\nReleased under the [MIT License](http://www.opensource.org/licenses/mit-license.php).\n","maintainers":[{"name":"satazor","email":"andremiguelcruz@msn.com"},{"name":"svnlto","email":"me@svenlito.com"},{"name":"wibblymat","email":"mat@wibbly.org.uk"}],"time":{"0.1.0-rc.1":"2013-07-09T19:56:01.226Z","0.1.0-rc.2":"2013-07-13T22:07:59.863Z","0.1.0-rc.3":"2013-07-20T18:49:52.595Z","0.1.0-rc.4":"2013-07-20T21:06:54.231Z","0.1.0-rc.5":"2013-07-24T08:01:29.621Z","0.1.0":"2013-07-27T21:31:28.857Z","0.1.1":"2013-07-28T02:18:45.468Z","0.1.2":"2013-08-03T11:44:41.170Z","0.1.3":"2013-08-05T22:41:20.801Z","0.1.4":"2013-08-20T00:03:33.982Z","0.1.5":"2013-09-28T14:11:57.919Z","0.1.6":"2013-12-17T13:22:09.998Z"},"author":{"name":"Twitter"},"repository":{"type":"git","url":"git://github.com/bower/registry-client.git"},"_attachments":{"bower-registry-client-0.1.6.tgz":{"content_type":"application/octet-stream","revpos":29,"digest":"md5-oa3uLT0Cnma7OkR7aVPJ0g==","length":17670,"stub":true},"bower-registry-client-0.1.5.tgz":{"content_type":"application/octet-stream","revpos":26,"digest":"md5-w7EMR0yYsxUESfEZFfZyow==","length":17546,"stub":true},"bower-registry-client-0.1.4.tgz":{"content_type":"application/octet-stream","revpos":24,"digest":"md5-o4+zgOdtjmssxU8q8IUBKw==","length":17358,"stub":true},"bower-registry-client-0.1.3.tgz":{"content_type":"application/octet-stream","revpos":22,"digest":"md5-C2J1CZ8Zn1KPHzQTqiIe8Q==","length":17351,"stub":true},"bower-registry-client-0.1.2.tgz":{"content_type":"application/octet-stream","revpos":20,"digest":"md5-SBoDJohVG0assc2n1PA7jQ==","length":17342,"stub":true},"bower-registry-client-0.1.1.tgz":{"content_type":"application/octet-stream","revpos":18,"digest":"md5-82niW4/ztbGZQlXY2JS1rw==","length":17257,"stub":true},"bower-registry-client-0.1.0.tgz":{"content_type":"application/octet-stream","revpos":12,"digest":"md5-OoEgXugjvlO1BHyrSYsCSw==","length":17592,"stub":true},"bower-registry-client-0.1.0-rc.5.tgz":{"content_type":"application/octet-stream","revpos":10,"digest":"md5-cN/Cb2V1GX7A+NmvQk92Og==","length":17477,"stub":true},"bower-registry-client-0.1.0-rc.4.tgz":{"content_type":"application/octet-stream","revpos":8,"digest":"md5-FZ+wEnexbs6cRzrMkeDENA==","length":17019,"stub":true},"bower-registry-client-0.1.0-rc.3.tgz":{"content_type":"application/octet-stream","revpos":6,"digest":"md5-xP2dzWAq0qOf+9EBAQ4gQw==","length":16788,"stub":true},"bower-registry-client-0.1.0-rc.2.tgz":{"content_type":"application/octet-stream","revpos":4,"digest":"md5-T0GM8yobWtEL77UEvGD1TQ==","length":16714,"stub":true},"bower-registry-client-0.1.0-rc.1.tgz":{"content_type":"application/octet-stream","revpos":2,"digest":"md5-iwJ6whxVlJ1BvRmVfjEb2g==","length":16413,"stub":true}},"_etag":"\"2J5NUV9TYR9AU9N8DJ8P8X3B3\""}